fbapy/__init__.py
fbapy/_api.py
fbapy/_consts.py
fbapy/_fbapy.py
fbapy/_utils.py
fbapy/_apis/__init__.py
fbapy/_apis/_edit_message.py
fbapy/_apis/_listen_mqtt.py
fbapy/_apis/_send_message.py
fbapy/_apis/_send_sticker.py
fbapy/_apis/_graphql/__init__.py
fbapy/_apis/_graphql/_change_bio_graphql.py
fbapy/_apis/_graphql/_create_new_group_graphql.py
fbapy/_apis/_graphql/_set_pfp_graphql.py
fbapy/_apis/_graphql/_share_story_graphql.py
fbapy/_apis/_http/__init__.py
fbapy/_apis/_http/_add_user_to_group_http.py
fbapy/_apis/_http/_change_emoji_http.py
fbapy/_apis/_http/_change_nickname_http.py
fbapy/_apis/_http/_get_user_info_http.py
fbapy/_apis/_http/_read_status_http.py
fbapy/_apis/_http/_remove_user_from_group_http.py
fbapy/_apis/_http/_resolve_photo_url_http.py
fbapy/_apis/_http/_send_message_http.py
fbapy/_apis/_http/_set_typing_http.py
fbapy/_apis/_http/_unsend_message_http.py
fbapy-1.0.2.dist-info/LICENSE
fbapy-1.0.2.dist-info/METADATA
fbapy-1.0.2.dist-info/WHEEL
fbapy-1.0.2.dist-info/top_level.txt
fbapy-1.0.2.dist-info/RECORD
