Metadata-Version: 2.1
Name: fbapy
Version: 1.0.2
Summary: Unofficial Facebook Chat API for Python
Home-page: https://github.com/RFS-ADRENO/fbapy
Author: RFS-ADRENO (RDU), KhangPhan27 (KhangPhan)
Keywords: facebook,messenger,chat,api,python,unofficial
License-File: LICENSE
